[
  {
    "id": "_12136722_1",
    "parentId": "_12136886_1",
    "title": "Seminar 1 Learning Guide and Seminar Questions",
    "body": "<div data-layout-row=\"166dd817-39b1-4665-8e9b-1a310cbf1198\"><div data-layout-column=\"4b4057fd-3542-44c9-8985-eb5198bb07bf\" data-layout-column-width=\"12\"><div data-bbid=\"bbml-editor-id_796069ac-6481-46f8-a91b-3579207aa425\"><br><p><a href=\"https://learn.uq.edu.au/bbcswebdav/pid-12136722-dt-content-rid-97381137_1/xid-97381137_1?Kq3cZcYS15=72501d55390d4d7f84a9c34f302e8821&VxJw3wfC56=1772364906&3cCnGYSz89=hTRd8rZRanHZ%2FYFKi7fEESBKQYNRGo%2Fq5SsoHekaLRQ%3D\" data-bbtype=\"attachment\" data-bbfile=\"{&quot;alternativeText&quot;:&quot;Workshop 1 Learning Guide and Workshop Questions To Prepare.docx&quot;,&quot;displayName&quot;:&quot;Workshop 1 Learning Guide and Workshop Questions To Prepare.docx&quot;,&quot;fileName&quot;:&quot;Workshop 1 Learning Guide and Workshop Questions To Prepare.docx&quot;,&quot;fileSize&quot;:82490,&quot;mimeType&quot;:&quot;application/vnd.openxmlformats-officedocument.wordprocessingml.document&quot;,&quot;render&quot;:&quot;inline&quot;,&quot;resourceUrl&quot;:&quot;https://learn.uq.edu.au/bbcswebdav/pid-12136722-dt-content-rid-97381137_1/xid-97381137_1?Kq3cZcYS15=72501d55390d4d7f84a9c34f302e8821&VxJw3wfC56=1772364906&3cCnGYSz89=hTRd8rZRanHZ%2FYFKi7fEESBKQYNRGo%2Fq5SsoHekaLRQ%3D&quot;,&quot;linkName&quot;:&quot;Workshop 1 Learning Guide and Workshop Questions To Prepare.docx&quot;,&quot;viewerUrl&quot;:&quot;https://learn.uq.edu.au/bbcswebdav/pid-12136722-dt-content-rid-97381137_1/xid-97381137_1?Kq3cZcYS15=72501d55390d4d7f84a9c34f302e8821&VxJw3wfC56=1772364906&3cCnGYSz89=hTRd8rZRanHZ%2FYFKi7fEESBKQYNRGo%2Fq5SsoHekaLRQ%3D?locale=en_GB&amp;isInlineRender=true&amp;xythos-download=true&amp;render=inline&quot;}\">Workshop 1 Learning Guide and Workshop Questions To Prepare.docx</a></p><br></div></div></div>",
    "created": "2025-01-07T03:29:26.218Z",
    "modified": "2026-02-22T12:08:57.368Z",
    "position": -1,
    "launchInNewWindow": false,
    "reviewable": false,
    "availability": {
      "available": "Yes",
      "allowGuests": true,
      "allowObservers": true,
      "adaptiveRelease": {}
    },
    "contentHandler": {
      "id": "resource/x-bb-document"
    },
    "links": [
      {
        "href": "/ultra/redirect?redirectType=nautilus&courseId=_196877_1&contentId=_12136722_1&parentId=_12136886_1",
        "rel": "alternate",
        "title": "User Interface View",
        "type": "text/html"
      }
    ]
  }
]